prima/__init__.py
prima/configuration/__init__.py
prima/configuration/utils/__init__.py
prima/configuration/utils/depreciationHandler.py
prima/configuration/utils/policyAggregation.py
prima/configuration/utils/userDefinedObject.py
prima/engine/__init__.py
prima/engine/execution.py
prima/engine/simulation.py
prima/engine/utils.py
prima/utils/__init__.py
prima/utils/execution.py
prima/utils/jupyter.py
prima/utils/sys_config.py
prima-0.1.0.dist-info/LICENSE.txt
prima-0.1.0.dist-info/WHEEL
prima-0.1.0.dist-info/METADATA
prima-0.1.0.dist-info/RECORD
