Metadata-Version: 2.1
Name: prima
Version: 0.1.0
Summary: 
Author: kivo360
Author-email: kivo360@gmail.com
Requires-Python: >=3.9,<3.11
Classifier: Programming Language :: Python :: 3
Classifier: Programming Language :: Python :: 3.10
Classifier: Programming Language :: Python :: 3.9
Requires-Dist: dill (>=0.3.4,<0.4.0)
Requires-Dist: fn (>=0.4.3,<0.5.0)
Requires-Dist: funcy (>=1.17,<2.0)
Requires-Dist: matplotlib (>=3.5.1,<4.0.0)
Requires-Dist: networkx (>=2.6.3,<3.0.0)
Requires-Dist: numpy (>=1.22.2,<2.0.0)
Requires-Dist: pandas (>=1.4.1,<2.0.0)
Requires-Dist: parameterized (>=0.8.1,<0.9.0)
Requires-Dist: pathos (>=0.2.8,<0.3.0)
Requires-Dist: plotly (>=5.6.0,<6.0.0)
Requires-Dist: pytest (>=7.0.1,<8.0.0)
Requires-Dist: pytz (>=2021.3,<2022.0)
Requires-Dist: scikit-learn (>=1.0.2,<2.0.0)
Requires-Dist: scipy (>=1.8.0,<2.0.0)
Requires-Dist: seaborn (>=0.11.2,<0.12.0)
Requires-Dist: six (>=1.16.0,<2.0.0)
Requires-Dist: tabulate (>=0.8.9,<0.9.0)
Requires-Dist: wheel (>=0.37.1,<0.38.0)
Requires-Dist: xarray (>=0.21.1,<0.22.0)
